LICENSE.txt
MANIFEST.in
README.md
requirements_dev.txt
setup.cfg
setup.py
goverge/__init__.py
goverge/_pkg_meta.py
goverge/coverage.py
goverge/main.py
goverge/reports.py
goverge.egg-info/PKG-INFO
goverge.egg-info/SOURCES.txt
goverge.egg-info/dependency_links.txt
goverge.egg-info/entry_points.txt
goverge.egg-info/top_level.txt