Metadata-Version: 1.0
Name: goverge
Version: 0.0.8
Summary: Go Coverage Tool for multi package coverage reporting.
Home-page: https://github.com/Workiva/goverge
Author: Wesley Balvanz
Author-email: wesley.balvanz@workiva.com
License: Copyright 2016 Workiva, INC
